<?xml version="1.0" encoding="utf-8" ?>
<elements>
	<info>
		<name>Barbarian Hatred</name>
		<update version="1.0.10">
			<file name="hatred.xml" url="https://raw.githubusercontent.com/MordecaiSir/elements/master/vindavia/hatred.xml" />
		</update>
	</info>
	
	<!-- place your elements here -->
	<element name="Path of the Hatred" type="Archetype" source="Vindavia" id="ID_MS_VRPG_ARCHETYPE_BARBARIAN_PATH_OF_THE_HATRED">
		<supports>Primal Path</supports>
		<description>
			<p>Barbarians who walk the Path of the Hatred draw their rage from a emotion burning within their souls.</p>
			<p class="indent">You can choose the reason of your hatred or determine it by rolling on the Origin of the Hatred table.</p>
			<h5 class="caption">Origin of the Hatred</h5>
			<table>
				<thead>
					<tr><td>d4</td><td>Origin</td></tr>
				</thead>
				<tr><td>1</td><td>Lorem Ipsum 1.</td></tr>
				<tr><td>2</td><td>Lorem Ipsum 2.</td></tr>
				<tr><td>3</td><td>Lorem Ipsum 3.</td></tr>
				<tr><td>4</td><td>Lorem Ipsum 4.</td></tr>
			</table>
			<div element="ID_MS_VRPG_ARCHETYPE_FEATURE_PATH_OF_THE_HATRED_HATRED" />
			<div element="ID_MS_VRPG_ARCHETYPE_FEATURE_PATH_OF_THE_HATRED_UNTIL_LAST_ENEMY_DIES" />
			<div element="ID_MS_VRPG_ARCHETYPE_FEATURE_PATH_OF_THE_HATRED_MONSTER_IN_FRONT_OF_ME" />
			<div element="ID_MS_VRPG_ARCHETYPE_FEATURE_PATH_OF_THE_HATRED_CONTINUE_THE_MASSACRE" />
		</description>
		<sheet display="false" />
		<rules>
			<grant type="Archetype Feature" id="ID_MS_VRPG_ARCHETYPE_FEATURE_PATH_OF_THE_HATRED_HATRED" level="3" />
			<grant type="Archetype Feature" id="ID_MS_VRPG_ARCHETYPE_FEATURE_PATH_OF_THE_HATRED_UNTIL_LAST_ENEMY_DIES" level="6" />
			<grant type="Archetype Feature" id="ID_MS_VRPG_ARCHETYPE_FEATURE_PATH_OF_THE_HATRED_MONSTER_IN_FRONT_OF_ME" level="10" />
			<grant type="Archetype Feature" id="ID_MS_VRPG_ARCHETYPE_FEATURE_PATH_OF_THE_HATRED_CONTINUE_THE_MASSACRE" level="14" />
		</rules>
	</element>
	<element name="HATRED" type="Archetype Feature" source="Vindavia" id="ID_MS_VRPG_ARCHETYPE_FEATURE_PATH_OF_THE_HATRED_HATRED">
		<description>
			<p><em>3rd-level Path of the Hatred feature</em></p>
			<p>Starting when you choose this path at 3rd level, while you are raging Reckless Attack becomes Wild Strikes.</p>
			<p style="text-indent: -1em; margin-left: 1em">Your attacks/weapons deal more damage (This bonus increases as you level). 3rd 1d4, 6th 1d6, 10th 1d8, 14th 1d12.</p>
			<p style="text-indent: -1em; margin-left: 1em">All of your attacks made with advantage.</p>
			<p style="text-indent: -1em; margin-left: 1em">All attacks against you made with advantage.</p>
			<p style="text-indent: -1em; margin-left: 1em">You take extra damage all forms of attacks (spells, magic items etc.). 3rd +1, 6th +2, 10th +3, 14th +4.</p>
		</description>
		<sheet>
			<description>
			<p>When you use Wild Strikes your attacks deal 1d{{wild strikes:damage}} and taking extra {{wild strikes:extra}} damage. </p>
			
			</description>
		</sheet>
		<rules>
			<stat name="wild strikes:damage" value="4" bonus="ability" level="3"/>
			<stat name="wild strikes:damage" value="6" bonus="ability" level="6"/>
			<stat name="wild strikes:damage" value="8" bonus="ability" level="10"/>
			<stat name="wild strikes:damage" value="12" bonus="ability" level="14"/>
			<stat name="wild strikes:extra" value="1" bonus="ability" level="3"/>
			<stat name="wild strikes:extra" value="2" bonus="ability" level="6"/>
			<stat name="wild strikes:extra" value="3" bonus="ability" level="10"/>
			<stat name="wild strikes:extra" value="4" bonus="ability" level="14"/>
		</rules>
	</element>
	
</elements>
